pcap/__about__.py
pcap/__init__.py
pcap/_pcap.py
pcap/_pcap_ex.py
pcap_ct-1.3.0b2.dist-info/LICENSE
pcap_ct-1.3.0b2.dist-info/METADATA
pcap_ct-1.3.0b2.dist-info/WHEEL
pcap_ct-1.3.0b2.dist-info/top_level.txt
pcap_ct-1.3.0b2.dist-info/zip-safe
pcap_ct-1.3.0b2.dist-info/RECORD
