Metadata-Version: 2.1
Name: pcap-ct
Version: 1.3.0b2
Summary: Python wrapper for the pcap library.
Author: Adam Karpierz
Author-email: adam@karpierz.net
Maintainer: Adam Karpierz
Maintainer-email: adam@karpierz.net
License: BSD license ; https://opensource.org/license/bsd-3-clause
Project-URL: Homepage, https://pypi.org/project/pcap-ct/
Project-URL: Documentation, https://pcap-ct.readthedocs.io/
Project-URL: Download, https://pypi.org/project/pcap-ct/
Project-URL: Source, https://github.com/karpierz/pcap-ct
Project-URL: Issues, https://github.com/karpierz/pcap-ct/issues
Keywords: pcap-ct,pcap,libpcap,pypcap,wpcap,npcap
Platform: any
Classifier: Development Status :: 4 - Beta
Classifier: Intended Audience :: Developers
Classifier: License :: OSI Approved :: BSD License
Classifier: Operating System :: OS Independent
Classifier: Natural Language :: Polish
Classifier: Programming Language :: Python
Classifier: Programming Language :: Python :: 3
Classifier: Programming Language :: Python :: 3.8
Classifier: Programming Language :: Python :: 3.9
Classifier: Programming Language :: Python :: 3.10
Classifier: Programming Language :: Python :: 3.11
Classifier: Programming Language :: Python :: 3.12
Classifier: Programming Language :: Python :: 3.13
Classifier: Programming Language :: Python :: 3 :: Only
Classifier: Programming Language :: Python :: Implementation :: CPython
Classifier: Programming Language :: Python :: Implementation :: PyPy
Classifier: Topic :: Software Development :: Libraries :: Python Modules
Requires-Python: <4.0.0,>=3.8.10
License-File: LICENSE
Requires-Dist: setuptools>=72.2.0
Requires-Dist: pkg-about>=1.1.8
Requires-Dist: libpcap>=1.11.0b10
Provides-Extra: doc
Requires-Dist: Sphinx>=7.1.2; extra == "doc"
Requires-Dist: sphinx-toolbox>=3.7.0; extra == "doc"
Requires-Dist: sphinx-tabs>=3.4.5; extra == "doc"
Requires-Dist: sphinx-copybutton>=0.5.2; extra == "doc"
Requires-Dist: sphinxcontrib-spelling>=8.0.0; extra == "doc"
Requires-Dist: sphinx-lint>=0.9.1; extra == "doc"
Requires-Dist: restructuredtext-lint>=1.4.0; extra == "doc"
Requires-Dist: nbsphinx>=0.9.4; extra == "doc"
Provides-Extra: test
Requires-Dist: deepdiff>=7.0.1; extra == "test"
Requires-Dist: rich>=13.7.1; extra == "test"
Requires-Dist: dpkt>=1.9.8; extra == "test"
